nci/__init__.py
nci/clients/__init__.py
nci/clients/iati/__init__.py
nci/clients/iati/extraction/__init__.py
nci/clients/iati/extraction/oct8ne.py
nci/clients/iati/transformation/__init__.py
nci/clients/iati/transformation/gmail.py
nci/clients/iati/transformation/oct8ne.py
nci/pipeline/__init__.py
nci/pipeline/logger_loader.py
nci/pipeline/pipeline.py
nci/pipeline/utils.py
tests/__init__.py
tests/import_tests.py
nci-0.0.4.dist-info/LICENSE
nci-0.0.4.dist-info/LICENSE.txt
nci-0.0.4.dist-info/METADATA
nci-0.0.4.dist-info/WHEEL
nci-0.0.4.dist-info/top_level.txt
nci-0.0.4.dist-info/RECORD
