Metadata-Version: 2.1
Name: nci
Version: 0.0.4
Summary: UNKNOWN
Home-page: UNKNOWN
Author: Miquel Escobar
Author-email: mec@novicell.es
License: MIT License
Requires-Dist: npyetl (==0.0.5)
Requires-Dist: azure-cosmosdb-table
Requires-Dist: pandas
